cohesion/__init__.py
cohesion/__main__.py
cohesion/filesystem.py
cohesion/flake8_extension.py
cohesion/module.py
cohesion/parser.py
cohesion-1.2.0.dist-info/LICENSE
cohesion-1.2.0.dist-info/METADATA
cohesion-1.2.0.dist-info/WHEEL
cohesion-1.2.0.dist-info/entry_points.txt
cohesion-1.2.0.dist-info/RECORD
