Metadata-Version: 2.1
Name: cohesion
Version: 1.2.0
Summary: A tool for measuring Python class cohesion.
Home-page: https://github.com/mschwager/cohesion
License: GPLv3
Requires-Python: >=3.8.1,<4.0.0
Classifier: Environment :: Console
Classifier: License :: OSI Approved :: GNU General Public License v3 (GPLv3)
Classifier: License :: Other/Proprietary License
Classifier: Operating System :: MacOS :: MacOS X
Classifier: Operating System :: Microsoft :: Windows
Classifier: Operating System :: POSIX
Classifier: Programming Language :: Python :: 3
Classifier: Programming Language :: Python :: 3.9
Classifier: Programming Language :: Python :: 3.10
Classifier: Programming Language :: Python :: 3.11
Classifier: Programming Language :: Python :: 3.12
Classifier: Programming Language :: Python :: 3.13
Classifier: Programming Language :: Python :: 3.14
Classifier: Topic :: Security
Classifier: Topic :: Software Development :: Quality Assurance
Project-URL: Repository, https://github.com/mschwager/cohesion
